## 什么是泛型

“泛型”的意思是参数化类型。使用该特性创建的类、接口以及方法，可以将类型作为参数指定所操作数据的类型。对于所有涉及泛型类的操作，泛型否可以自动确保类型安全。编译器无法在编译时期知道一个类型是否能强制转换为其他类型，所以如果不使用泛型，那么强制转换操作就有可能在运行期发生异常。使用泛型就可以在编译期发现这些问题，将运行期错误转换成编译时错误。

因为在 java 1.5 之前不支持泛型，所以需要为旧的、在支持泛型之前编写的代码提供一些过度路径。这些遗留代码既要保留功能又要和泛型兼容。为了处理泛型过渡，java允许使用泛型类而不提供任何类型参数。这会为类创建原始类型（raw type），这种原始类型与不使用泛型的遗留代码是兼容的，但这会使泛型类失去了它的安全性的特点。

## 擦除

为了与以前的 java 版本兼容，对于 java 语言的语法或JVM所做的任何修改都必须 避免破坏以前的代码，为了满足这一约束，java使用擦除实现泛型。

工作原理：编译 java 代码的时，所有泛型信息被移除（擦除）。这意味着要使用它们的界定类型替换参数类型，如果没有显示地指定界定类型，就是用Object，然后应用适当的类型转换（根据类型参数而定），以保持与类型参数所指定类型的兼容性。编译器也会强制实现这种类型兼容性。使用这种方式实现泛型，意味着在运行时没有类型参数。他们只是一种源代码机制，或者说泛型是java的语法糖。

java 规范：类型擦除是从可能包括参数化类型和类型变量到永远不是参数化类型或类型变量的类型的映射。我们将| T |符号用于表示擦除类型T。擦除映射定义如下:

- 擦除参数化类型 G`<`T1,...,Tn`>` is |G|.
- 嵌套类型的擦除 T`.`C is |T|.C.
- 删除数组类型 T`[]` is |T|`[]`.
- 类型变量的擦除是其最左边界的擦除。
- 每种其他类型的擦除都是类型本身.

类型擦除还将构造函数或方法的签名映射到没有参数化类型或类型变量的签名。删除构造函数或方法签名s是一个签名，由与s相同的名称和s中给出的所有形式参数类型的擦除组成。

如果擦除方法或构造函数的签名，则方法的返回类型和泛型方法或构造函数的类型参数也会被擦除。

擦除泛型方法的签名没有类型参数。

## 桥接方法

编译器偶尔需要为类添加桥接方法（bridge method），用于处理如下类型：子类中重写方法的类型擦除不能产生与超类中方法相同的擦除。对于这种情况，会生成使用超类类型擦除的方法，并且这个方法调用具有由子类指定的类型擦除的方法。用户不会看到，也不能使用。

例子：

```java
public interface MyClass<T> {


    public T test(T t);
}
```

```java
class BridgeClass implements MyClass<String> {
    @Override
    public String test(String s) {
        return null;
    }
}
```

在这个例子中，BeidgeClass 实现了 MyClass，但使用的是String版本。并且实现了MyClass接口的`test`方法。这并没有问题，但是因为需要实现接口的方法，而接口的界定类型为T，这样在擦除的时候接口就会生成如下字节码：

```
  public abstract T test(T);
    descriptor: (Ljava/lang/Object;)Ljava/lang/Object;
    flags: (0x0401) ACC_PUBLIC, ACC_ABSTRACT
    Signature: #12                          // (TT;)TT;


```

descriptor 描述方法的参数和返回值，那么接口里应该生成

```java
  public java.lang.Object test(java.lang.Object);
    descriptor: (Ljava/lang/Object;)Ljava/lang/Object;
    flags: (0x1041) ACC_PUBLIC, ACC_BRIDGE, ACC_SYNTHETIC
    Code:
      stack=2, locals=2, args_size=2
         0: aload_0
         1: aload_1
         2: checkcast     #2                  // class java/lang/String
         5: invokevirtual #3                  // Method test:(Ljava/lang/String;)Ljava/lang/String;
         8: areturn
      LineNumberTable:
        line 32: 0
      LocalVariableTable:
        Start  Length  Slot  Name   Signature
            0       9     0  this   Lgenerinc/MyGenerinc$BridgeClass;
```

但是由于子类实现的时候将接口的界定类型固定为 String，所以在子类中会生成如下的字节码：

```
  public java.lang.String test(java.lang.String);
    descriptor: (Ljava/lang/String;)Ljava/lang/String;
    flags: (0x0001) ACC_PUBLIC
    Code:
      stack=1, locals=2, args_size=2
         0: aconst_null
         1: areturn
      LineNumberTable:
        line 28: 0
      LocalVariableTable:
        Start  Length  Slot  Name   Signature
            0       2     0  this   Lgenerinc/MyGenerinc$BridgeClass;
            0       2     1     s   Ljava/lang/String;

```

子类中的返回类型和参数现在变成 String。但是这样不满足java语言规范，子类没有实现接口的方法。所以编译器主动为class文件中添加如下字节码。

```
  public java.lang.Object test(java.lang.Object);
    descriptor: (Ljava/lang/Object;)Ljava/lang/Object;
    flags: (0x1041) ACC_PUBLIC, ACC_BRIDGE, ACC_SYNTHETIC
    Code:
      stack=2, locals=2, args_size=2
         0: aload_0
         1: aload_1
         2: checkcast     #2                  // class java/lang/String
         5: invokevirtual #3                  // Method test:(Ljava/lang/String;)Ljava/lang/String;
         8: areturn
      LineNumberTable:
        line 32: 0
      LocalVariableTable:
        Start  Length  Slot  Name   Signature
            0       9     0  this   Lgenerinc/MyGenerinc$BridgeClass;

```

这个方法就是桥接方法，它的返回类型和参数类型都变成了Object，而且在它的 flags 标识中标记了 ACC_BRIDGE, ACC_SYNTHETIC。ACC_BRIDGE代表这是一个桥接方法，ACC_SYNTHETIC代表这个方法由编译器引入而不是由用户编写。这样就做到了与泛型与非泛型的兼容。也达到了桥接方法的目的，当生成的桥接方法不能当做重写方法时，桥接方法作为重写方法，达到java语言规范的要求。

### 模糊性错误

泛型的引入增加了一种新类型错误——模糊性错误的可能，当擦除导致两个看起来不同的泛型声明，在擦除之后变成相同的类型而导致冲突时，就会发生模糊性错误。比如

```java
public class MyClass<K,V> {
    //编译不通过
    public  void test(K k){}
    
    public  void test(V v){}
    
}
```

泛型类声明了两个泛型类型参数：K 和 V。然后根据类型参数重载`test`方法，这看起来符合语言规范，K和V在表面上看起来是两个不同的类型，但是事实来说K和V在编写代码创建对象的时候，不一定会是不同的类型。比如：

```java
var my = new MyClass<String,String>();
```

这完全可以，但是在擦除的时候K和V都会被String替换， 这种情况下`test`方法的两个版本就会完全相同，这肯定是错误的。

而且`test`类型擦会使两个版本都变成:

   ```java
public void  test(Object o){}
    
   ```

因此，在MyClass中重写`test`本身就是含糊不清的。

即使向下面这样修改,实例化：

```java
public class MyClass<K, V extends Number>
```

```java
var my = new MyClass<String, Number>();
```

这样可以通过编译并且正确运行，但是如果

```java
var my = new MyClass<Number, Number>();
my.test(new Integer("1"));

```

这样可以通过编译，但是在运行的时候会报： 对test的引用不明确的错误，所以为K和V设计两个不同名的方法而不是重载`test`方法，才是最好的。